[
  {
    "ID": 1,
    "username": "usuarioA",
    "password": "$2b$10$WValccndPVSz1UYaPQXOhe/V/H2RyNAf5.bUeJM8rOEfmBkYsgxyK",
    "channel":"1204717397521465394"
  },
  {
    "ID": 2,
    "username": "usuarioB",
    "password": "$2b$10$85nQ.P.eSrSkmMIalz4Ip.BShIVM2bJPhmN7UAcYbtjLpdGICwACK",
    "channel":"1210242180359393290"
  },
  {
    "ID": 3,
    "username": "usuarioC",
    "password": "$2b$10$DX/9Y2.dFyTKmB.CF4bAOuGAOSZc3IK01lkTpha3z83xT8zninFia",
    "channel":"1210242202488406088"
  }
]